mcp_data_analyzer/__init__.py
mcp_data_analyzer/__main__.py
mcp_data_analyzer/cli.py
mcp_data_analyzer/core.py
zmcp_data_analzyer-0.4.0.dist-info/METADATA
zmcp_data_analzyer-0.4.0.dist-info/WHEEL
zmcp_data_analzyer-0.4.0.dist-info/entry_points.txt
zmcp_data_analzyer-0.4.0.dist-info/top_level.txt
zmcp_data_analzyer-0.4.0.dist-info/RECORD
