Metadata-Version: 2.4
Name: zmcp-data-analzyer
Version: 0.4.0
Summary: sunnychou  zmcp_data_analyzer 
Author-email: SunnyChou <3560094104@qq.com>
Requires-Python: >=3.12
Requires-Dist: mcp[cli]>=1.13.1
Requires-Dist: pandas>=2.3.2
Requires-Dist: seaborn>=0.13.2
Requires-Dist: twine>=6.1.0
Requires-Dist: openpyxl>=3.1.5
